caseless/__init__.py
caseless-0.5.0.dist-info/LICENSE
caseless-0.5.0.dist-info/METADATA
caseless-0.5.0.dist-info/WHEEL
caseless-0.5.0.dist-info/RECORD
