Metadata-Version: 2.1
Name: caseless
Version: 0.5.0
Summary: A typed dictionary in Python with case-insensitive keys
Home-page: https://github.com/clintval/caseless
License: MIT
Keywords: caseless,case-insensitive,dictionary,python
Author: Clint Valentine
Author-email: valentine.clint@gmail.com
Requires-Python: >=3.8,<4.0
Classifier: Development Status :: 2 - Pre-Alpha
Classifier: Intended Audience :: Developers
Classifier: License :: OSI Approved :: MIT License
Classifier: Programming Language :: Python :: 3
Classifier: Programming Language :: Python :: 3.8
Classifier: Programming Language :: Python :: 3.9
Classifier: Programming Language :: Python :: 3.10
Classifier: Programming Language :: Python :: 3.11
Classifier: Programming Language :: Python :: 3.12
Project-URL: Bug Tracker, https://github.com/clintval/caseless/issues
Project-URL: Documentation, https://github.com/clintval/caseless
Project-URL: Repository, https://github.com/clintval/caseless
